[
  {
    "name": "Alpha Tutors",
    "email": "iratnere+test2@gmail.com",
    "phone": "555-123-4567",
    "address": "123 Tutor Ln",
    "website": "https://alphatutors.com",
    "city": "Concord, CA",
    "notes": "test run",
    "processed": ""
  },
  {
    "name": "Test Academy",
    "email": "iratnere+test1@gmail.com",
    "phone": "555-777-0007",
    "address": "777 Mission Blvd",
    "website": "https://testacademy.com",
    "city": "Mission City",
    "notes": "Test entry note",
    "processed": ""
  }
]